anigamerpy/__init__.py
anigamerpy/anime.py
anigamerpy/response/__init__.py
anigamerpy/response/allanime.py
anigamerpy/response/error.py
anigamerpy/response/newanime.py
anigamerpy/response/searchanime.py
anigamerpy-0.2.3.dist-info/LICENSE
anigamerpy-0.2.3.dist-info/METADATA
anigamerpy-0.2.3.dist-info/WHEEL
anigamerpy-0.2.3.dist-info/top_level.txt
anigamerpy-0.2.3.dist-info/RECORD
