Metadata-Version: 2.1
Name: anigamerpy
Version: 0.2.3
Summary: 動畫瘋爬蟲工具
Home-page: https://github.com/Sakuya0502/anigamerpy
Author: Sakuya0502
License: MIT
Platform: UNKNOWN
Classifier: Natural Language :: Chinese (Traditional)
Classifier: Operating System :: Microsoft :: Windows :: Windows 11
Classifier: Programming Language :: Python :: 3
Classifier: License :: OSI Approved :: MIT License
Requires: requests
Requires: bs4
